//
Compiled from "Qwe.java"
public class spbctf.re.Qwe {
  public spbctf.re.Qwe();
    Code:
       0: aload_0
       1: invokespecial #1                  // Method java/lang/Object."<init>":()V
       4: return

  public static void main(java.lang.String[]);
    Code:
       0: new           #2                  // class java/math/BigInteger
       3: dup
       4: aload_0
       5: iconst_0
       6: aaload
       7: invokespecial #3                  // Method java/math/BigInteger."<init>":(Ljava/lang/String;)V
      10: astore_1
// [1] = BigInt(args[0])
      11: new           #2                  // class java/math/BigInteger
      14: dup
      15: aload_0
      16: iconst_1
      17: aaload
      18: invokespecial #3                  // Method java/math/BigInteger."<init>":(Ljava/lang/String;)V
      21: astore_2
// [2] = BigInt(args[1])
      22: new           #2                  // class java/math/BigInteger
      25: dup
      26: aload_0
      27: iconst_2
      28: aaload
      29: invokespecial #3                  // Method java/math/BigInteger."<init>":(Ljava/lang/String;)V
      32: astore_3
// [3] = BigInt(args[2])
      33: getstatic     #4                  // Field java/math/BigInteger.ZERO:Ljava/math/BigInteger;
      36: astore        4
// [4] = BigInt(0)

  // [4] = max(0, [1])
      38: aload         4
      40: aload_1
      41: invokevirtual #5                  // Method java/math/BigInteger.compareTo:(Ljava/math/BigInteger;)I
// [4] <=> [1]
      44: ifge          60
      47: aload         4
      49: getstatic     #6                  // Field java/math/BigInteger.ONE:Ljava/math/BigInteger;
      52: invokevirtual #7                  // Method java/math/BigInteger.add:(Ljava/math/BigInteger;)Ljava/math/BigInteger;
      55: astore        4
      57: goto          38


      60: aload_2
      61: invokevirtual #8                  // Method java/math/BigInteger.longValue:()J
      64: l2i
      65: istore        5
// [5] = int([2])
      67: aload_2
      68: invokevirtual #8                  // Method java/math/BigInteger.longValue:()J
      71: lstore        6
// [6] = long([2])
      73: iconst_0
      74: istore        8
// [8] = 0
      76: iload         8
      78: iload         5
      80: if_icmpge     96 // [8] <=> [5]
      83: lload         6
      85: lload         6
      87: lmul
      88: lstore        6
// [6] = 36
      90: iinc          8, 1
      93: goto          76

// [8] = 2
      96: aload         4
      98: ldc2_w        #9                  // long 5l
     101: invokestatic  #11                 // Method java/math/BigInteger.valueOf:(J)Ljava/math/BigInteger;
     104: invokevirtual #12                 // Method java/math/BigInteger.multiply:(Ljava/math/BigInteger;)Ljava/math/BigInteger;
     107: astore        8
// [8] = [4] * 5 = max(0, [1]) * 5
     109: aload_2
     110: ldc2_w        #13                 // long 4l
     113: invokestatic  #11                 // Method java/math/BigInteger.valueOf:(J)Ljava/math/BigInteger;
     116: invokevirtual #12                 // Method java/math/BigInteger.multiply:(Ljava/math/BigInteger;)Ljava/math/BigInteger;
     119: astore        9
// [9] = [2] * 4
     121: aload_3
     122: ldc2_w        #13                 // long 4l
     125: invokestatic  #11                 // Method java/math/BigInteger.valueOf:(J)Ljava/math/BigInteger;
     128: invokevirtual #12                 // Method java/math/BigInteger.multiply:(Ljava/math/BigInteger;)Ljava/math/BigInteger;
     131: astore        10
// [10] = [3] * 4
     133: aload         8
     135: aload         9
     137: invokevirtual #7                  // Method java/math/BigInteger.add:(Ljava/math/BigInteger;)Ljava/math/BigInteger;
     140: aload         10
     142: invokevirtual #7                  // Method java/math/BigInteger.add:(Ljava/math/BigInteger;)Ljava/math/BigInteger;
     145: ldc2_w        #15                 // long 11l
     148: invokestatic  #11                 // Method java/math/BigInteger.valueOf:(J)Ljava/math/BigInteger;
     151: invokevirtual #17                 // Method java/math/BigInteger.equals:(Ljava/lang/Object;)Z
// [8] + [9] + [10] == 11
// max(0, [1]) * 5 + [2] * 4 + [3] * 4 == 11
     154: ifne          166 // we want them to be equal
     157: getstatic     #18                 // Field java/lang/System.out:Ljava/io/PrintStream;
     160: ldc           #19                 // String nope
     162: invokevirtual #20                 // Method java/io/PrintStream.println:(Ljava/lang/String;)V
     165: return

     166: aload         4
     168: ldc2_w        #13                 // long 4l
     171: invokestatic  #11                 // Method java/math/BigInteger.valueOf:(J)Ljava/math/BigInteger;
     174: invokevirtual #12                 // Method java/math/BigInteger.multiply:(Ljava/math/BigInteger;)Ljava/math/BigInteger;
     177: astore        8
// [8] = [4] * 4 = max(0, [1]) * 4
     179: aload_2
     180: ldc2_w        #9                  // long 5l
     183: invokestatic  #11                 // Method java/math/BigInteger.valueOf:(J)Ljava/math/BigInteger;
     186: invokevirtual #12                 // Method java/math/BigInteger.multiply:(Ljava/math/BigInteger;)Ljava/math/BigInteger;
     189: astore        9
// [9] = 5 * [2]
     191: aload_3
     192: ldc2_w        #13                 // long 4l
     195: invokestatic  #11                 // Method java/math/BigInteger.valueOf:(J)Ljava/math/BigInteger;
     198: invokevirtual #12                 // Method java/math/BigInteger.multiply:(Ljava/math/BigInteger;)Ljava/math/BigInteger;
     201: astore        10
// [10] = [3] * 4
     203: aload         8
     205: aload         9
     207: invokevirtual #7                  // Method java/math/BigInteger.add:(Ljava/math/BigInteger;)Ljava/math/BigInteger;
     210: aload         10
     212: invokevirtual #7                  // Method java/math/BigInteger.add:(Ljava/math/BigInteger;)Ljava/math/BigInteger;
     215: ldc2_w        #21                 // long 8l
     218: invokestatic  #11                 // Method java/math/BigInteger.valueOf:(J)Ljava/math/BigInteger;
     221: invokevirtual #17                 // Method java/math/BigInteger.equals:(Ljava/lang/Object;)Z
// [8] + [9] + [10] == 8
// max(0, [1]) * 4 + 5 * [2] + [3] * 4 == 8
     224: ifne          236
     227: getstatic     #18                 // Field java/lang/System.out:Ljava/io/PrintStream;
     230: ldc           #19                 // String nope
     232: invokevirtual #20                 // Method java/io/PrintStream.println:(Ljava/lang/String;)V
     235: return

     236: aload         4
     238: ldc2_w        #13                 // long 4l
     241: invokestatic  #11                 // Method java/math/BigInteger.valueOf:(J)Ljava/math/BigInteger;
     244: invokevirtual #12                 // Method java/math/BigInteger.multiply:(Ljava/math/BigInteger;)Ljava/math/BigInteger;
     247: astore        8
// [8] = [4] * 4 = max(0, [1]) * 4
     249: aload_2
     250: ldc2_w        #13                 // long 4l
     253: invokestatic  #11                 // Method java/math/BigInteger.valueOf:(J)Ljava/math/BigInteger;
     256: invokevirtual #12                 // Method java/math/BigInteger.multiply:(Ljava/math/BigInteger;)Ljava/math/BigInteger;
     259: astore        9
// [9] = [2] * 4
     261: aload_3
     262: ldc2_w        #9                  // long 5l
     265: invokestatic  #11                 // Method java/math/BigInteger.valueOf:(J)Ljava/math/BigInteger;
     268: invokevirtual #12                 // Method java/math/BigInteger.multiply:(Ljava/math/BigInteger;)Ljava/math/BigInteger;
     271: astore        10
// [10] = [3] * 5
     273: aload         8
     275: aload         9
     277: invokevirtual #7                  // Method java/math/BigInteger.add:(Ljava/math/BigInteger;)Ljava/math/BigInteger;
     280: aload         10
     282: invokevirtual #7                  // Method java/math/BigInteger.add:(Ljava/math/BigInteger;)Ljava/math/BigInteger;
     285: ldc2_w        #23                 // long 7l
     288: invokestatic  #11                 // Method java/math/BigInteger.valueOf:(J)Ljava/math/BigInteger;
     291: invokevirtual #17                 // Method java/math/BigInteger.equals:(Ljava/lang/Object;)Z
// [8] + [9] + [10] == 7
// max([1], 0) * 4 + [2] * 4 + [3] * 5 == 7
     294: ifne          306
     297: getstatic     #18                 // Field java/lang/System.out:Ljava/io/PrintStream;
     300: ldc           #19                 // String nope
     302: invokevirtual #20                 // Method java/io/PrintStream.println:(Ljava/lang/String;)V
     305: return

     306: aload_2
     307: getstatic     #6                  // Field java/math/BigInteger.ONE:Ljava/math/BigInteger;
     310: invokevirtual #25                 // Method java/math/BigInteger.subtract:(Ljava/math/BigInteger;)Ljava/math/BigInteger;
     313: astore        11
// [11] = [2] - 1
     315: new           #2                  // class java/math/BigInteger
     318: dup
     319: ldc           #26                 // String cafebabedeadbeef
     321: bipush        16
     323: invokespecial #27                 // Method java/math/BigInteger."<init>":(Ljava/lang/String;I)V
// put 0xcafebabedeadbeef
     326: aload         11
     328: invokevirtual #12                 // Method java/math/BigInteger.multiply:(Ljava/math/BigInteger;)Ljava/math/BigInteger;
     331: aload         4
     333: invokevirtual #12                 // Method java/math/BigInteger.multiply:(Ljava/math/BigInteger;)Ljava/math/BigInteger;
     336: aload_3
     337: invokevirtual #12                 // Method java/math/BigInteger.multiply:(Ljava/math/BigInteger;)Ljava/math/BigInteger;
     340: astore        12
// [12] = [1] * [4] * [3] * 0xcafebabedeadbeef
     342: getstatic     #18                 // Field java/lang/System.out:Ljava/io/PrintStream;
     345: ldc           #28                 // String bingo spbctf{%s}\n
     347: iconst_1
     348: anewarray     #29                 // class java/lang/Object
     351: dup
     352: iconst_0
     353: aload         12
     355: aastore
     356: invokevirtual #30                 // Method java/io/PrintStream.printf:(Ljava/lang/String;[Ljava/lang/Object;)Ljava/io/PrintStream;
     359: pop
     360: return
}

// 5x + 4y + 4z = 11; 4x + 5y + 4z = 8;  x * 4 + y * 4 + z * 5 = 7
// 3, 0, -1
//  0xcafebabedeadbeef * -1 * 3 *  -1
// spbctf{43882001906065292493}